LICENSE.txt
README.md
setup.py
Pear2Pear.egg-info/PKG-INFO
Pear2Pear.egg-info/SOURCES.txt
Pear2Pear.egg-info/dependency_links.txt
Pear2Pear.egg-info/requires.txt
Pear2Pear.egg-info/top_level.txt
pear2pear/GenHandler.py
pear2pear/GenUtils.py
pear2pear/__init__.py
pear2pear/dataset_1h.csv
pear2pear/dataset_new_1h.csv
pear2pear/outputToPinCode.py