Metadata-Version: 2.4
Name: Pear2Pear
Version: 0.1.9
Summary: Pear2Pear package
Home-page: https://github.com/vanouri/P2P_EIP_PUB_Package
Author: Nouri valentin
Author-email: valentin.nouri20@gmail.com
License: BSD 2-clause
License-File: LICENSE.txt
Requires-Dist: mpi4py>=2.0
Requires-Dist: numpy
Requires-Dist: multiprocess==0.70.18
Requires-Dist: numba==0.62.1
Requires-Dist: numpy==2.3.3
Requires-Dist: pandas==2.3.3
Dynamic: author
Dynamic: author-email
Dynamic: description
Dynamic: description-content-type
Dynamic: home-page
Dynamic: license
Dynamic: license-file
Dynamic: requires-dist
Dynamic: summary
